{"cameraMode":{"drawMode":0,"name":"Shaded","section":"Shading Mode"},"sceneLighting":false,"audioPlay":false,"sceneViewState":{"m_AlwaysRefresh":false,"showFog":true,"showSkybox":false,"showFlares":true,"showImageEffects":true,"showParticleSystems":true,"showVisualEffectGraphs":true,"m_FxEnabled":true},"in2DMode":false,"pivot":{"x":0.948131263256073,"y":3.0385072231292726,"z":-1.009260892868042},"rotation":{"x":-0.45087969303131106,"y":-0.013403601944446564,"z":0.006839228793978691,"w":-0.8926651477813721},"size":0.6752862334251404,"orthographic":false}